hyperproof/__init__.py
hyperproof/controls_api.py
hyperproof/custom_apps_api.py
hyperproof/labels_api.py
hyperproof/programs_api.py
hyperproof/proof_api.py
hyperproof/risks_api.py
hyperproof/roles_api.py
hyperproof/task_statuses_api.py
hyperproof/tasks_api.py
hyperproof/users_api.py
hyperproof/utils.py
hyperproof-1.0.0.dist-info/METADATA
hyperproof-1.0.0.dist-info/WHEEL
hyperproof-1.0.0.dist-info/top_level.txt
hyperproof-1.0.0.dist-info/RECORD
