Metadata-Version: 2.1
Name: hyperproof
Version: 1.0.0
Summary: A Python wrapper for all Hyperproof APIs
Home-page: https://github.com/booyasatoshi/hyperproof
Author: Virgil Vaduva
Author-email: vvaduva@gmail.com
Classifier: Programming Language :: Python :: 3
Classifier: License :: OSI Approved :: GNU General Public License (GPL)
Classifier: Operating System :: OS Independent
Requires-Python: >=3.9
Requires-Dist: requests >=2.25.1
Requires-Dist: python-dotenv >=1.0.1
